{"appleSKU":"UtmostGamesBulletproof","appleTeamID":"LJCXSCUKHA","enableCodelessAutoInitialization":true,"products":[{"id":"UTMC100","type":0,"storeIDs":[{"store":"AppleAppStore","id":"gold_100_apple"},{"store":"GooglePlay","id":"gold_100_google"}],"defaultDescription":{"googleLocale":4,"title":"Gold Bag","description":"Increase gold by 100"},"screenshotPath":"C:/Users/mmusa/Desktop/gold100.PNG","applePriceTier":1,"xiaomiPriceTier":0,"googlePrice":{"data":[99,0,0,131072],"num":0.99},"pricingTemplateID":"","descriptions":[{"googleLocale":30,"title":"Alt\\u0131n Kesesi","description":"Alt\\u0131n\\u0131 100 art\\u0131r\\u0131r"}],"payouts":[]},{"id":"UTMC500","type":0,"storeIDs":[{"store":"AppleAppStore","id":"gold_500_apple"},{"store":"GooglePlay","id":"gold_500_google"}],"defaultDescription":{"googleLocale":4,"title":"Gold Case","description":"Increase gold by 500"},"screenshotPath":"C:/Users/mmusa/Desktop/gold500.PNG","applePriceTier":2,"xiaomiPriceTier":0,"googlePrice":{"data":[199,0,0,131072],"num":1.99},"pricingTemplateID":"","descriptions":[{"googleLocale":30,"title":"Alt\\u0131n \\u00c7antas\\u0131","description":"Alt\\u0131n\\u0131 500 art\\u0131r\\u0131r"}],"payouts":[]},{"id":"UTMC1000","type":0,"storeIDs":[{"store":"AppleAppStore","id":"gold_1000_apple"},{"store":"GooglePlay","id":"gold_1000_google"}],"defaultDescription":{"googleLocale":4,"title":"Gold Chest","description":"Increase gold by 1000"},"screenshotPath":"C:/Users/mmusa/Desktop/gold1000.PNG","applePriceTier":3,"xiaomiPriceTier":0,"googlePrice":{"data":[299,0,0,131072],"num":2.99},"pricingTemplateID":"","descriptions":[{"googleLocale":30,"title":"Alt\\u0131n Sand\\u0131\\u011f\\u0131","description":"Alt\\u0131n\\u0131 1000 art\\u0131r\\u0131r"}],"payouts":[]}]}